{
  "type": "article",
  "authors": [
    "Dulvy NK",
    "Pacoureau N",
    "Rigby CL",
    "Pollom RA",
    "Jabado RW",
    "Ebert DA",
    "Finucci B",
    "Pollock CM",
    "Cheok J",
    "Derrick DH",
    "Herman KB",
    "Sherman CS",
    "VanderWright WJ",
    "Lawson JM",
    "Walls RHL",
    "Carlson JK",
    "Charvet P",
    "Bineesh KK",
    "Fernando D",
    "Ralph GM",
    "Matsushiba JH",
    "Hilton-Taylor C",
    "Fordham SV",
    "Simpfendorfer CA"
  ],
  "year": 2021,
  "title": "Overfishing drives over one-third of all sharks and rays toward a global extinction crisis",
  "container": "Current Biology",
  "volume": "31",
  "issue": "21",
  "pages": "4773-4787.e8",
  "doi": "10.1016/j.cub.2021.08.062",
  "url": "https://www.cell.com/current-biology/fulltext/S0960-9822(21)01182-9",
  "accessedDate": "2026-06-13",
  "note": "Global reassessment finding roughly one-third of chondrichthyans are threatened, driven primarily by overfishing."
}
